README.md
setup.py
pulumi_bitwarden/__init__.py
pulumi_bitwarden/_inputs.py
pulumi_bitwarden/_utilities.py
pulumi_bitwarden/attachment.py
pulumi_bitwarden/folder.py
pulumi_bitwarden/get_attachment.py
pulumi_bitwarden/get_folder.py
pulumi_bitwarden/get_item_login.py
pulumi_bitwarden/get_item_secure_note.py
pulumi_bitwarden/get_org_collection.py
pulumi_bitwarden/get_organization.py
pulumi_bitwarden/item_login.py
pulumi_bitwarden/item_secure_note.py
pulumi_bitwarden/org_collection.py
pulumi_bitwarden/outputs.py
pulumi_bitwarden/provider.py
pulumi_bitwarden/pulumi-plugin.json
pulumi_bitwarden/py.typed
pulumi_bitwarden.egg-info/PKG-INFO
pulumi_bitwarden.egg-info/SOURCES.txt
pulumi_bitwarden.egg-info/dependency_links.txt
pulumi_bitwarden.egg-info/not-zip-safe
pulumi_bitwarden.egg-info/requires.txt
pulumi_bitwarden.egg-info/top_level.txt
pulumi_bitwarden/config/__init__.py
pulumi_bitwarden/config/vars.py