Metadata-Version: 2.1
Name: pulumi-bitwarden
Version: 0.8.0a1
Summary: A Pulumi package for creating and managing Bitwarden resources
Home-page: https://github.com/MaienM/pulumi-bitwarden
License: Apache-2.0
Project-URL: Repository, https://github.com/MaienM/pulumi-bitwarden
Keywords: pulumi bitwarden category/utility
Requires-Python: >=3.8
